lins_servico/__init__.py
lins_servico/decorators.py
lins_servico/exceptions.py
lins_servico/thread.py
lins_servico/utils.py
lins_servico-1.1.0.15.dist-info/METADATA
lins_servico-1.1.0.15.dist-info/WHEEL
lins_servico-1.1.0.15.dist-info/top_level.txt
lins_servico-1.1.0.15.dist-info/RECORD
