Metadata-Version: 2.1
Name: lins-servico
Version: 1.1.0.15
Summary: Pacote para gerenciar servicos atraves de threads
Home-page: https://bitbucket.org/grupolinsferrao/pypck-servico/
Author: Gustavo Schaedler
Author-email: gustavopoa@gmail.com
License: MIT
Platform: UNKNOWN
Classifier: Programming Language :: Python :: 3
Classifier: License :: OSI Approved :: MIT License
Classifier: Operating System :: OS Independent
Requires-Python: >=3
